md2html/__init__.py
md2html/cli.py
md2html/converter.py
md2html/templates/base.html
md2html/tests/__init__.py
md2html/tests/test_cli.py
md2html/tests/test_converter.py
md2html_math-0.1.5.dist-info/METADATA
md2html_math-0.1.5.dist-info/WHEEL
md2html_math-0.1.5.dist-info/entry_points.txt
md2html_math-0.1.5.dist-info/top_level.txt
md2html_math-0.1.5.dist-info/RECORD
