Metadata-Version: 2.4
Name: md2html-math
Version: 0.1.5
Summary: A markdown to HTML converter with LaTeX math support and beautiful styling
Home-page: https://github.com/marcoallanda01/md2html-math
Author: Marco Allanda
Author-email: marcoallanda@gmail.com
Classifier: Programming Language :: Python :: 3
Classifier: License :: OSI Approved :: MIT License
Classifier: Operating System :: OS Independent
Requires-Python: >=3.11
Requires-Dist: markdown>=3.8
Requires-Dist: jinja2>=3.0.0
Requires-Dist: python-markdown-math>=0.8
Requires-Dist: pymdown-extensions>=10.0.0
Provides-Extra: dev
Requires-Dist: pytest>=8.0.0; extra == "dev"
Requires-Dist: pytest-cov>=6.0.0; extra == "dev"
Dynamic: author
Dynamic: author-email
Dynamic: classifier
Dynamic: description
Dynamic: description-content-type
Dynamic: home-page
Dynamic: provides-extra
Dynamic: requires-dist
Dynamic: requires-python
Dynamic: summary
